aiosolr.py
aiosolr-5.0.2.dist-info/LICENSE.md
aiosolr-5.0.2.dist-info/WHEEL
aiosolr-5.0.2.dist-info/METADATA
aiosolr-5.0.2.dist-info/RECORD
