Metadata-Version: 2.1
Name: aiosolr
Version: 5.0.2
Summary: Lightweight AsyncIO Python client for Apache Solr
Keywords: solr,asyncio,aiohttp,search
Author-email: Brad Belyeu <bradley.belyeu@youversion.com>
Requires-Python: >=3.10
Classifier: Intended Audience :: Developers
Classifier: License :: OSI Approved :: MIT License
Classifier: Operating System :: OS Independent
Classifier: Programming Language :: Python
Classifier: Topic :: Internet :: WWW/HTTP :: Indexing/Search
Classifier: Programming Language :: Python :: 3
Requires-Dist: aiohttp >= 3.8
Requires-Dist: bleach >= 6
Project-URL: Home, https://github.com/bbelyeu/aiosolr
